affinidi_tdk_vault_data_manager_client/__init__.py
affinidi_tdk_vault_data_manager_client/api/__init__.py
affinidi_tdk_vault_data_manager_client/api/accounts_api.py
affinidi_tdk_vault_data_manager_client/api/configuration_api.py
affinidi_tdk_vault_data_manager_client/api/files_api.py
affinidi_tdk_vault_data_manager_client/api/nodes_api.py
affinidi_tdk_vault_data_manager_client/api/profile_data_api.py
affinidi_tdk_vault_data_manager_client/api/well_known_api.py
affinidi_tdk_vault_data_manager_client/api_client.py
affinidi_tdk_vault_data_manager_client/api_response.py
affinidi_tdk_vault_data_manager_client/configuration.py
affinidi_tdk_vault_data_manager_client/exceptions.py
affinidi_tdk_vault_data_manager_client/models/__init__.py
affinidi_tdk_vault_data_manager_client/models/account_dto.py
affinidi_tdk_vault_data_manager_client/models/aws_credential_exchange_operation_ok.py
affinidi_tdk_vault_data_manager_client/models/consumer_metadata_dto.py
affinidi_tdk_vault_data_manager_client/models/cors_aws_credential_exchange_ok.py
affinidi_tdk_vault_data_manager_client/models/cors_delete_account_ok.py
affinidi_tdk_vault_data_manager_client/models/cors_delete_node_ok.py
affinidi_tdk_vault_data_manager_client/models/cors_get_config_ok.py
affinidi_tdk_vault_data_manager_client/models/cors_get_configuration_ok.py
affinidi_tdk_vault_data_manager_client/models/cors_get_scanned_file_info_ok.py
affinidi_tdk_vault_data_manager_client/models/cors_get_well_known_jwks_ok.py
affinidi_tdk_vault_data_manager_client/models/cors_init_nodes_ok.py
affinidi_tdk_vault_data_manager_client/models/cors_list_accounts_ok.py
affinidi_tdk_vault_data_manager_client/models/cors_list_node_children_ok.py
affinidi_tdk_vault_data_manager_client/models/cors_list_root_node_children_ok.py
affinidi_tdk_vault_data_manager_client/models/cors_list_scanned_files_ok.py
affinidi_tdk_vault_data_manager_client/models/cors_move_node_ok.py
affinidi_tdk_vault_data_manager_client/models/cors_permanently_delete_node_ok.py
affinidi_tdk_vault_data_manager_client-1.66.0.dist-info/METADATA
affinidi_tdk_vault_data_manager_client-1.66.0.dist-info/WHEEL
affinidi_tdk_vault_data_manager_client-1.66.0.dist-info/RECORD
